profile_reaction_local/__init__.py
profile_reaction_local/constants_profile_reaction.py
profile_reaction_local/profile_reaction.py
profile_reaction_local/profile_reaction_dto.py
profile_reaction_local-0.0.25.dist-info/METADATA
profile_reaction_local-0.0.25.dist-info/WHEEL
profile_reaction_local-0.0.25.dist-info/top_level.txt
profile_reaction_local-0.0.25.dist-info/RECORD
