Metadata-Version: 2.4
Name: profile-reaction-local
Version: 0.0.25
Summary: PyPI Package for Circles Profile Reaction Local Python
Home-page: https://github.com/circles-zone/profile-reaction-local-python-package
Author: Circles
Author-email: info@circlez.ai
Classifier: Programming Language :: Python :: 3
Classifier: License :: Other/Proprietary License
Classifier: Operating System :: OS Independent
Requires-Dist: database-mysql-local>=0.0.199
Requires-Dist: logger-local>=0.0.133
Dynamic: author
Dynamic: author-email
Dynamic: classifier
Dynamic: description
Dynamic: description-content-type
Dynamic: home-page
Dynamic: requires-dist
Dynamic: summary
